README.rst
setup.py
zdb/__init__.py
zdb/db.py
zdb.egg-info/PKG-INFO
zdb.egg-info/SOURCES.txt
zdb.egg-info/dependency_links.txt
zdb.egg-info/top_level.txt
zdb/queries/__init__.py
zdb/queries/mssql.py
zdb/queries/mysql.py
zdb/queries/pg.py
zdb/queries/redshift.py
zdb/queries/sqlite.py