Metadata-Version: 1.0
Name: zdb
Version: 0.1.2
Summary: a db package that doesn't suck
Home-page: https://github.com/yhat/zdb/
Author: Greg Lamp
Author-email: greg@yhathq.com
License: BSD
Platform: UNKNOWN
